{
	"info": {
		"_postman_id": "a1b2c3d4-e5f6-7890-1234-56789abcdef0",
		"name": "Doctorna API",
		"description": "RESTful API endpoints for the Doctorna Clinic Management System.",
		"schema": "https://schema.getpostman.com/json/collection/v2.1.0/collection.json"
	},
	"item": [
		{
			"name": "Users",
			"item": [
				{
					"name": "Get All Users",
					"request": {
						"method": "GET",
						"header": [],
						"url": {
							"raw": "{{base_url}}/users",
							"host": [
								"{{base_url}}"
							],
							"path": [
								"users"
							]
						}
					}
				}
			]
		},
		{
			"name": "Doctors",
			"item": [
				{
					"name": "Get All Doctors",
					"request": {
						"method": "GET",
						"header": [],
						"url": {
							"raw": "{{base_url}}/doctors",
							"host": [
								"{{base_url}}"
							],
							"path": [
								"doctors"
							]
						}
					}
				}
			]
		},
		{
			"name": "Appointments",
			"item": [
				{
					"name": "Get All Appointments",
					"request": {
						"method": "GET",
						"header": [],
						"url": {
							"raw": "{{base_url}}/appointments",
							"host": [
								"{{base_url}}"
							],
							"path": [
								"appointments"
							]
						}
					}
				}
			]
		},
		{
			"name": "Specialities",
			"item": [
				{
					"name": "Get All Specialities",
					"request": {
						"method": "GET",
						"header": [],
						"url": {
							"raw": "{{base_url}}/specialities",
							"host": [
								"{{base_url}}"
							],
							"path": [
								"specialities"
							]
						}
					}
				}
			]
		},
		{
			"name": "Sub Services",
			"item": [
				{
					"name": "Get All Sub Services",
					"request": {
						"method": "GET",
						"header": [],
						"url": {
							"raw": "{{base_url}}/sub-services",
							"host": [
								"{{base_url}}"
							],
							"path": [
								"sub-services"
							]
						}
					}
				}
			]
		}
	],
	"variable": [
		{
			"key": "base_url",
			"value": "http://localhost:8000/routes/api.php",
			"type": "string"
		}
	]
}
